abstract_windows/__init__.py
abstract_windows/browser_utils/__init__.py
abstract_windows/browser_utils/browser_utils.py
abstract_windows/string_comp/__init__.py
abstract_windows/string_comp/string_compare.py
abstract_windows/window_utils/__init__.py
abstract_windows/window_utils/idle_uitils.py
abstract_windows/window_utils/idle_utils.py
abstract_windows/window_utils/instance_utils.py
abstract_windows/window_utils/monitor_utils.py
abstract_windows/window_utils/mons.py
abstract_windows/window_utils/window_utils.py
abstract_windows/window_utils___/__init__.py
abstract_windows/window_utils___/idle_uitils.py
abstract_windows/window_utils___/idle_utils.py
abstract_windows/window_utils___/instance_utils.py
abstract_windows/window_utils___/monitor_utils.py
abstract_windows/window_utils___/mons.py
abstract_windows/window_utils___/window_core.py
abstract_windows/window_utils___/window_utils.py
abstract_windows-0.0.21.dist-info/METADATA
abstract_windows-0.0.21.dist-info/WHEEL
abstract_windows-0.0.21.dist-info/top_level.txt
abstract_windows-0.0.21.dist-info/RECORD
